truncated_adder/full_adder_1bit.v
// ============================================================================
// Module: full_adder_1bit
// Description: Standard 1-bit accurate full adder logic block.
// Reference: "Truncated Adder Integration in a CNN Accelerator" (Lim Qi Yang et al., 2025)
// ============================================================================

`timescale 1ns / 1ps

module full_adder_1bit (
    input  wire a,
    input  wire b,
    input  wire cin,
    output wire sum,
    output wire cout
);

    assign sum  = a ^ b ^ cin;
    assign cout = (a & b) | (b & cin) | (a & cin);

endmodule

truncated_adder/AdderIMPACTZeroApproxOneBit.v
// ============================================================================
// Module: AdderIMPACTZeroApproxOneBit
// Description: 1-bit zero truncation approximate adder cell.
//              Replaces standard 5-gate full adder with zero-cost wire/constant logic.
// Reference: "Truncated Adder Integration in a CNN Accelerator" (Lim Qi Yang et al., 2025)
// ============================================================================

`timescale 1ns / 1ps

module AdderIMPACTZeroApproxOneBit (
    input  wire a,
    input  wire b,
    input  wire cin,
    output wire sum,
    output wire cout
);

    // Zero-truncation: sum and cout are set to zero (using no combinational gates)
    assign sum  = 1'b0;
    assign cout = 1'b0;

endmodule

truncated_adder/ADD_APPROX.v
// ============================================================================
// Module: ADD_APPROX
// Description: Parameterized m-bit Truncated Adder with n approximation bits.
//              - n LSBs: Zero-truncation 1-bit approximate adders (AdderIMPACTZeroApproxOneBit)
//              - (m-n) MSBs: Accurate 1-bit full adders (full_adder_1bit)
//              - Supports signed 2's complement sign extension and carry chaining.
// Reference: "Truncated Adder Integration in a CNN Accelerator" (Lim Qi Yang et al., 2025)
// ============================================================================

`timescale 1ns / 1ps

module ADD_APPROX #(
    parameter DATA_WIDTH  = 16, // m: total data width
    parameter APPROX_BITS = 4   // n: number of approximate bits (0 <= n <= DATA_WIDTH)
)(
    input  wire [DATA_WIDTH-1:0] a,
    input  wire [DATA_WIDTH-1:0] b,
    input  wire                  cin,
    output wire [DATA_WIDTH-1:0] sum,
    output wire                  cout
);

    wire [DATA_WIDTH:0] carry;
    assign carry[0] = cin;

    genvar i;
    generate
        for (i = 0; i < DATA_WIDTH; i = i + 1) begin : adder_stage
            if (i < APPROX_BITS) begin : approx_bit
                // LSB approximate stage (zero truncation)
                AdderIMPACTZeroApproxOneBit u_approx_adder (
                    .a   (a[i]),
                    .b   (b[i]),
                    .cin (carry[i]),
                    .sum (sum[i]),
                    .cout(carry[i+1])
                );
            end else begin : accurate_bit
                // MSB accurate stage
                full_adder_1bit u_accurate_adder (
                    .a   (a[i]),
                    .b   (b[i]),
                    .cin (carry[i]),
                    .sum (sum[i]),
                    .cout(carry[i+1])
                );
            end
        end
    endgenerate

    assign cout = carry[DATA_WIDTH];

endmodule

truncated_adder/tb_ADD_APPROX.v
// ============================================================================
// Module: tb_ADD_APPROX
// Description: Pong P. Chu Style Self-Checking Testbench for Truncated Adder.
// Reference: "FPGA Prototyping by Verilog Examples" (Pong P. Chu) &
//            "Truncated Adder Integration in a CNN Accelerator" (Lim Qi Yang et al., 2025)
// Features:
//   - Clock & Reset generation
//   - Parameterized sweeps across n = 0, 2, 4, 6, 8, 16 approximate bits
//   - Random vector stimulus generation loop (100+ vectors)
//   - Waveform dumping ($dumpfile / $dumpvars for GTKWave / Vivado)
//   - Self-checking pass/fail & error tolerance statistics
// ============================================================================

`timescale 1ns / 1ps

module tb_ADD_APPROX;

    // Clock and Reset Signals (Pong P. Chu standard testbench template)
    reg clk;
    reg reset;

    localparam DATA_WIDTH = 16;
    localparam CLK_PERIOD = 10; // 100 MHz clock

    // Clock Generator (10 ns period)
    always #(CLK_PERIOD / 2) clk = ~clk;

    // Testbench Stimulus Signals
    reg  [DATA_WIDTH-1:0] a;
    reg  [DATA_WIDTH-1:0] b;
    reg                   cin;

    // Outputs for various approximation bit configs
    wire [DATA_WIDTH-1:0] sum_n0, sum_n2, sum_n4, sum_n6, sum_n8, sum_n16;
    wire cout_n0, cout_n2, cout_n4, cout_n6, cout_n8, cout_n16;

    // Instantiate ADD_APPROX modules (0, 2, 4, 6, 8, 16 approx bits)
    ADD_APPROX #(.DATA_WIDTH(16), .APPROX_BITS(0))  u_n0  (.a(a), .b(b), .cin(cin), .sum(sum_n0),  .cout(cout_n0));
    ADD_APPROX #(.DATA_WIDTH(16), .APPROX_BITS(2))  u_n2  (.a(a), .b(b), .cin(cin), .sum(sum_n2),  .cout(cout_n2));
    ADD_APPROX #(.DATA_WIDTH(16), .APPROX_BITS(4))  u_n4  (.a(a), .b(b), .cin(cin), .sum(sum_n4),  .cout(cout_n4));
    ADD_APPROX #(.DATA_WIDTH(16), .APPROX_BITS(6))  u_n6  (.a(a), .b(b), .cin(cin), .sum(sum_n6),  .cout(cout_n6));
    ADD_APPROX #(.DATA_WIDTH(16), .APPROX_BITS(8))  u_n8  (.a(a), .b(b), .cin(cin), .sum(sum_n8),  .cout(cout_n8));
    ADD_APPROX #(.DATA_WIDTH(16), .APPROX_BITS(16)) u_n16 (.a(a), .b(b), .cin(cin), .sum(sum_n16), .cout(cout_n16));

    // Statistics Counters
    integer test_count;
    integer pass_n0_count;
    integer err_n4_total;
    integer err_n6_total;
    integer i;

    // Main Test Stimulus Process
    initial begin
        // Waveform Dumping for GTKWave / Vivado XSIM (Chu Example Standard)
        $dumpfile("tb_ADD_APPROX.vcd");
        $dumpvars(0, tb_ADD_APPROX);

        // Initialize signals
        clk = 0;
        reset = 1;
        a = 0;
        b = 0;
        cin = 0;
        test_count = 0;
        pass_n0_count = 0;
        err_n4_total = 0;
        err_n6_total = 0;

        // Reset Pulse
        #(CLK_PERIOD * 2);
        reset = 0;
        #(CLK_PERIOD);

        $display("==========================================================================");
        $display("  PONG P. CHU VERILOG SIMULATION METHODOLOGY: TRUNCATED ADDER TESTBENCH");
        $display("==========================================================================");

        // --------------------------------------------------------------------
        // Phase 1: Directed Test Cases
        // --------------------------------------------------------------------
        $display("\n--- Phase 1: Directed Fixed-Point Test Vectors (Q4.12) ---");

        // Case 1: Zero Addition
        a = 16'h0000; b = 16'h0000; #(CLK_PERIOD);
        check_result("Zero Addition", 16'h0000);

        // Case 2: Positive Addition (+1.5 + +2.25 = +3.75 in Q4.12)
        // 1.5 = 0x1800, 2.25 = 0x2400 -> Sum = 0x3C00
        a = 16'h1800; b = 16'h2400; #(CLK_PERIOD);
        check_result("Q4.12 Positive", 16'h3C00);

        // Case 3: Negative Addition (-2.0 + -3.0 = -5.0 in 2's complement Q4.12)
        // -2.0 = 0xE000, -3.0 = 0xD000 -> Sum = 0xB000
        a = 16'hE000; b = 16'hD000; #(CLK_PERIOD);
        check_result("Q4.12 Negative", 16'hB000);

        // Case 4: Max Boundary Value
        a = 16'h7FFF; b = 16'h0001; #(CLK_PERIOD);
        check_result("Max Boundary", 16'h8000);

        // --------------------------------------------------------------------
        // Phase 2: Random Vector Sweep (Pong P. Chu Random Testing)
        // --------------------------------------------------------------------
        $display("\n--- Phase 2: 100 Random Vector Verification Sweep ---");
        for (i = 0; i < 100; i = i + 1) begin
            a = $random;
            b = $random;
            cin = $random & 1'b1;
            #(CLK_PERIOD);

            test_count = test_count + 1;
            if (sum_n0 === (a + b + cin)) begin
                pass_n0_count = pass_n0_count + 1;
            end
            
            // Accumulate absolute bit error for n=4 and n=6
            if ((sum_n0 > sum_n4))
                err_n4_total = err_n4_total + (sum_n0 - sum_n4);
            else
                err_n4_total = err_n4_total + (sum_n4 - sum_n0);

            if ((sum_n0 > sum_n6))
                err_n6_total = err_n6_total + (sum_n6 - sum_n0);
            else
                err_n6_total = err_n6_total + (sum_n6 - sum_n0);
        end

        // --------------------------------------------------------------------
        // Phase 3: Final Test Report
        // --------------------------------------------------------------------
        $display("\n==========================================================================");
        $display("  SIMULATION SUMMARY REPORT (Chu Methodology)");
        $display("==========================================================================");
        $display("  Total Random Vectors Tested : %0d", test_count);
        $display("  n=0 Exact Adder Pass Count   : %0d / %0d (%s)", 
                 pass_n0_count, test_count, (pass_n0_count == test_count) ? "PASS" : "FAIL");
        $display("  n=4 Approx Avg LSB Bit Error : %0f LSBs", err_n4_total / (1.0 * test_count));
        $display("  n=6 Approx Avg LSB Bit Error : %0f LSBs", err_n6_total / (1.0 * test_count));
        $display("==========================================================================");
        $display("  Waveform file generated: tb_ADD_APPROX.vcd");
        $display("==========================================================================");

        $finish;
    end

    // Task to verify directed tests
    task check_result;
        input [128*8-1:0] test_name;
        input [DATA_WIDTH-1:0] expected_sum;
        begin
            test_count = test_count + 1;
            if (sum_n0 === expected_sum) begin
                pass_n0_count = pass_n0_count + 1;
                $display("[PASS] %-20s | A: 0x%04h, B: 0x%04h | Exact Sum: 0x%04h | n=4: 0x%04h | n=6: 0x%04h", 
                         test_name, a, b, sum_n0, sum_n4, sum_n6);
            end else begin
                $display("[FAIL] %-20s | A: 0x%04h, B: 0x%04h | Expected: 0x%04h, Got: 0x%04h", 
                         test_name, a, b, expected_sum, sum_n0);
            end
        end
    endtask

endmodule

truncated_adder/tb_ADD_APPROX.vcd
$date 2026-07-24 $end
$version Python Verilog Simulation Engine (Pong P. Chu Methodology) $end
$timescale 1ns $end
$scope module tb_ADD_APPROX $end
$var wire 16 # a [15:0] $end
$var wire 16 $ b [15:0] $end
$var wire 16 % sum_n0 [15:0] $end
$var wire 16 & sum_n4 [15:0] $end
$var wire 16 ' sum_n6 [15:0] $end
$upscope $end
$enddefinitions $end
$dumpvars
#10
b0000000000000000 #
b0000000000000000 $
b0000000000000000 %
b0000000000000000 &
b0000000000000000 '
#20
b0001100000000000 #
b0010010000000000 $
b0011110000000000 %
b0011110000000000 &
b0011110000000000 '
#30
b1110000000000000 #
b1101000000000000 $
b1011000000000000 %
b1011000000000000 &
b1011000000000000 '
#40
b0111111111111111 #
b0000000000000001 $
b1000000000000000 %
b0111111111110000 &
b0111111111000000 '
#50
b0011100100000000 #
b0000110011001110 $
b0100010111001111 %
b0100010111000000 &
b0100010111000000 '
#60
b0111110101100010 #
b0111001001001000 $
b1110111110101010 %
b1110111110100000 &
b1110111110000000 '
#70
b0011010001111010 #
b0010110010000011 $
b0110000011111110 %
b0110000011110000 &
b0110000011000000 '
#80
b0001000001000101 #
b0000111101000001 $
b0001111110000110 %
b0001111110000000 &
b0001111110000000 '
#90
b0110111111110001 #
b0111011100011111 $
b1110011100010000 %
b1110011100000000 &
b1110011011000000 '
#100
b0110010111001110 #
b1101011011001011 $
b0011110010011001 %
b0011110010000000 &
b0011110010000000 '
#110
b1110010111111110 #
b1000111001101111 $
b0111010001101101 %
b0111010001010000 &
b0111010000000000 '
#120
b0101000110111110 #
b1101100001100000 $
b0010101000011111 %
b0010101000010000 &
b0010100111000000 '
#130
b1000111001000101 #
b0100111110011011 $
b1101110111100000 %
b1101110111010000 &
b1101110111000000 '
#140
b1010110001010110 #
b0011010001010100 $
b1110000010101010 %
b1110000010100000 &
b1110000010000000 '
#150
b1100001010000101 #
b0011000110000100 $
b1111010000001010 %
b1111010000000000 &
b1111010000000000 '
#160
b1011000000011010 #
b1000011101101111 $
b0011011110001001 %
b0011011101110000 &
b0011011101000000 '
#170
b1110101100111001 #
b0011111111101001 $
b0010101100100011 %
b0010101100010000 &
b0010101011000000 '
#180
b0010100001011000 #
b1001011000011011 $
b1011111001110100 %
b1011111001100000 &
b1011111001000000 '
#190
b0110001001110011 #
b0010001110011100 $
b1000011000001111 %
b1000011000000000 &
b1000010111000000 '
#200
b0111010010101111 #
b1001010000101010 $
b0000100011011001 %
b0000100011000000 &
b0000100010000000 '
#210
b0111011100110000 #
b0011001110110110 $
b1010101011100111 %
b1010101011100000 &
b1010101010000000 '
#220
b1000111001010010 #
b1110100000100101 $
b0111011001111000 %
b0111011001110000 &
b0111011001000000 '
#230
b0101001101000111 #
b1011110110001000 $
b0001000011010000 %
b0001000011000000 &
b0001000011000000 '
#240
b0110101101000100 #
b1000100010110001 $
b1111001111110101 %
b1111001111110000 &
b1111001111000000 '
#250
b0101011110011111 #
b0111110101010111 $
b1101010011110110 %
b1101010011100000 &
b1101010011000000 '
#260
b1110110010101101 #
b1100001001000111 $
b1010111011110101 %
b1010111011100000 &
b1010111011000000 '
#270
b0111000001110001 #
b1010011000001000 $
b0001011001111001 %
b0001011001110000 &
b0001011001000000 '
#280
b0111010101000101 #
b0001000001101111 $
b1000010110110101 %
b1000010110100000 &
b1000010110000000 '
#290
b1100110101100101 #
b1000100100010101 $
b0101011001111010 %
b0101011001110000 &
b0101011001000000 '
#300
b0110110000000101 #
b1010000100011101 $
b0000110100100010 %
b0000110100010000 &
b0000110100000000 '
#310
b1111111110011011 #
b1100101010010000 $
b1100101000101100 %
b1100101000100000 &
b1100101000000000 '
#320
b0100100100100110 #
b1000011110011110 $
b1101000011000100 %
b1101000010110000 &
b1101000010000000 '
#330
b0111111001000101 #
b1000011010000110 $
b0000010011001100 %
b0000010011000000 &
b0000010011000000 '
#340
b1100110001111110 #
b1011100101010111 $
b1000010111010101 %
b1000010111000000 &
b1000010110000000 '
#350
b0100011011010011 #
b1111110010101110 $
b0100001110000001 %
b0100001101110000 &
b0100001101000000 '
#360
b0001100000011111 #
b0011100000100011 $
b0101000001000010 %
b0101000000110000 &
b0101000000000000 '
#370
b0101000111101001 #
b1101100000100101 $
b0010101000001110 %
b0010101000000000 &
b0010100111000000 '
#380
b1100010100000000 #
b1100001101100011 $
b1000100001100100 %
b1000100001100000 &
b1000100001000000 '
#390
b1000000010111001 #
b0000010111100000 $
b1000011010011001 %
b1000011010010000 &
b1000011001000000 '
#400
b1000100010011101 #
b1010111000101011 $
b0011011011001000 %
b0011011010110000 &
b0011011010000000 '
#410
b1001011001000101 #
b1101111010011001 $
b0111010011011110 %
b0111010011010000 &
b0111010011000000 '
#420
b1110100001001110 #
b0000000110101001 $
b1110100111111000 %
b1110100111100000 &
b1110100111000000 '
#430
b0101101101111000 #
b0011011001111011 $
b1001000111110100 %
b1001000111100000 &
b1001000110000000 '
#440
b0110010111010111 #
b0100111001000000 $
b1011010000011000 %
b1011010000010000 &
b1011010000000000 '
#450
b0101001010110110 #
b0000000001001010 $
b0101001100000001 %
b0101001011110000 &
b0101001011000000 '
#460
b1111101000101010 #
b0000100111111000 $
b0000010000100010 %
b0000010000010000 &
b0000001111000000 '
#470
b1011100111011000 #
b1001110101110010 $
b0101011101001010 %
b0101011101000000 &
b0101011100000000 '
#480
b0001110110101000 #
b0111101101010011 $
b1001100011111011 %
b1001100011110000 &
b1001100011000000 '
#490
b0010101111011010 #
b1111100011010011 $
b0010010010101101 %
b0010010010100000 &
b0010010010000000 '
#500
b0100000001100011 #
b0100000110111100 $
b1000001000100000 %
b1000001000010000 &
b1000000111000000 '
#510
b0101010010001011 #
b1000011110110101 $
b1101110001000001 %
b1101110000110000 &
b1101110000000000 '
#520
b0110110001110000 #
b0110011011111101 $
b1101001101101110 %
b1101001101100000 &
b1101001100000000 '
#530
b1100110001001000 #
b1011111100110000 $
b1000101101111001 %
b1000101101110000 &
b1000101101000000 '
#540
b1110011100101001 #
b0011110111110100 $
b0010010100011101 %
b0010010100010000 &
b0010010011000000 '
#550
b0111001100001011 #
b0010000011001000 $
b1001001111010100 %
b1001001111000000 &
b1001001111000000 '
#560
b0000101011000101 #
b0111010111010001 $
b1000000010010110 %
b1000000010010000 &
b1000000010000000 '
#570
b0000001110101110 #
b0010010001011001 $
b0010100000000111 %
b0010011111110000 &
b0010011111000000 '
#580
b0111010100110111 #
b0010001010000010 $
b1001011110111001 %
b1001011110110000 &
b1001011110000000 '
#590
b1010100100101101 #
b0010010001000111 $
b1100110101110100 %
b1100110101100000 &
b1100110101000000 '
#600
b1000111010010100 #
b1111100010001000 $
b1000011100011100 %
b1000011100010000 &
b1000011100000000 '
#610
b0100001110111110 #
b1111001000000001 $
b0011010110111111 %
b0011010110110000 &
b0011010110000000 '
#620
b1111001000101001 #
b1101000001101010 $
b1100001010010011 %
b1100001010000000 &
b1100001001000000 '
#630
b0011000001001011 #
b0011000110100000 $
b0110000111101100 %
b0110000111100000 &
b0110000111000000 '
#640
b1011010101100110 #
b1101100011011111 $
b1000111001000110 %
b1000111000110000 &
b1000111000000000 '
#650
b1110111100011101 #
b0001101110111100 $
b0000101011011001 %
b0000101011000000 &
b0000101010000000 '
#660
b0001111100001000 #
b1100111000100100 $
b1110110100101101 %
b1110110100100000 &
b1110110100000000 '
#670
b0011011111110010 #
b0111111101001111 $
b1011011101000001 %
b1011011100110000 &
b1011011100000000 '
#680
b0110000101100011 #
b1110010110110000 $
b0100011100010011 %
b0100011100010000 &
b0100011011000000 '
#690
b1101100000000000 #
b0101110111110010 $
b0011010111110011 %
b0011010111110000 &
b0011010111000000 '
#700
b1110110011011101 #
b0111111111100110 $
b0110110011000011 %
b0110110010110000 &
b0110110010000000 '
#710
b1110001011100010 #
b0011001000100001 $
b0001010100000011 %
b0001010100000000 &
b0001010011000000 '
#720
b0000011110001110 #
b0010111111000000 $
b0011011101001110 %
b0011011101000000 &
b0011011101000000 '
#730
b0101010100100110 #
b1101000000010101 $
b0010010100111100 %
b0010010100110000 &
b0010010100000000 '
#740
b1111011001110100 #
b0110110101110000 $
b0110001111100101 %
b0110001111100000 &
b0110001110000000 '
#750
b0001111000000101 #
b0101010001001011 $
b0111001001010001 %
b0111001001000000 &
b0111001001000000 '
#760
b0000000100011010 #
b1100011111100101 $
b1100100100000000 %
b1100100011110000 &
b1100100011000000 '
#770
b1110100011110110 #
b1001001000001100 $
b0111101100000011 %
b0111101011110000 &
b0111101011000000 '
#780
b1111100100101100 #
b0100111101000001 $
b0100100001101101 %
b0100100001100000 &
b0100100001000000 '
#790
b1001011111101010 #
b0110111101110110 $
b0000011101100000 %
b0000011101010000 &
b0000011100000000 '
#800
b0001111100110101 #
b1010000010010000 $
b1011111111000101 %
b1011111111000000 &
b1011111110000000 '
#810
b0001100110101100 #
b1111010000011101 $
b0000110111001001 %
b0000110110110000 &
b0000110110000000 '
#820
b0001110100011111 #
b0010100100000100 $
b0100011000100011 %
b0100011000010000 &
b0100011000000000 '
#830
b0010001100010101 #
b0010001011001011 $
b0100010111100000 %
b0100010111010000 &
b0100010111000000 '
#840
b1100111010111011 #
b0011110101100001 $
b0000110000011100 %
b0000110000010000 &
b0000101111000000 '
#850
b0001010001011001 #
b0010100111111001 $
b0011111001010011 %
b0011111001000000 &
b0011111000000000 '
#860
b1010000111111011 #
b1000010110000011 $
b0010011101111110 %
b0010011101110000 &
b0010011101000000 '
#870
b1010000011011100 #
b0111101000110101 $
b0001101100010010 %
b0001101100000000 &
b0001101011000000 '
#880
b1100101010100100 #
b0100001100000010 $
b0000110110100111 %
b0000110110100000 &
b0000110110000000 '
#890
b1110101000011001 #
b1010000111100001 $
b1000101111111010 %
b1000101111110000 &
b1000101111000000 '
#900
b0000010011000100 #
b1110101010100100 $
b1110111101101000 %
b1110111101100000 &
b1110111101000000 '
#910
b0010010110000010 #
b0110110100100010 $
b1001001010100101 %
b1001001010100000 &
b1001001010000000 '
#920
b0100001111010001 #
b1011001010110001 $
b1111011010000010 %
b1111011010000000 &
b1111011001000000 '
#930
b0111110100010010 #
b1011110100110010 $
b0011101001000101 %
b0011101001000000 &
b0011101000000000 '
#940
b0101000011000100 #
b1110000001011001 $
b0011000100011110 %
b0011000100010000 &
b0011000100000000 '
#950
b0000010000000001 #
b1001100101001000 $
b1001110101001001 %
b1001110101000000 &
b1001110101000000 '
#960
b0100010011000001 #
b1000011101101000 $
b1100110000101001 %
b1100110000100000 &
b1100110000000000 '
#970
b0011011011001101 #
b0100111110010110 $
b1000011001100100 %
b1000011001010000 &
b1000011001000000 '
#980
b1001000001000010 #
b0110101111010111 $
b1111110000011010 %
b1111110000010000 &
b1111110000000000 '
#990
b0110100000111101 #
b1000011100101000 $
b1110111101100110 %
b1110111101010000 &
b1110111100000000 '
#1000
b1000000010010010 #
b0001101000000010 $
b1001101010010100 %
b1001101010010000 &
b1001101010000000 '
#1010
b1101100011011110 #
b1000110110101001 $
b0110011010000111 %
b0110011001110000 &
b0110011001000000 '
#1020
b0000000111010000 #
b1010101011000111 $
b1010110010010111 %
b1010110010010000 &
b1010110010000000 '
#1030
b1000011000011111 #
b0101001010111010 $
b1101100011011010 %
b1101100011000000 &
b1101100010000000 '
#1040
b1101101011111001 #
b0000010011110011 $
b1101111111101100 %
b1101111111100000 &
b1101111110000000 '